Metadata-Version: 2.1
Name: translated
Version: 0.1
Summary: Fast text translate, running on the engine - googletrans.
Home-page: UNKNOWN
Author-email: beeeirym@gmail.com
License: UNKNOWN
Platform: UNKNOWN
